aact_openhands/README.md
aact_openhands/__init__.py
aact_openhands/app.py
aact_openhands/openhands_node.py
aact_openhands/run_tests.sh
aact_openhands/tests/__init__.py
aact_openhands/tests/test_live_server.py
aact_openhands/tests/test_server.py
aact_openhands/utils.py
openhands/README.md
openhands/__init__.py
openhands/agenthub/README.md
openhands/agenthub/__init__.py
openhands/agenthub/browsing_agent/README.md
openhands/agenthub/browsing_agent/__init__.py
openhands/agenthub/browsing_agent/browsing_agent.py
openhands/agenthub/browsing_agent/prompt.py
openhands/agenthub/browsing_agent/response_parser.py
openhands/agenthub/browsing_agent/utils.py
openhands/agenthub/codeact_agent/README.md
openhands/agenthub/codeact_agent/__init__.py
openhands/agenthub/codeact_agent/action_parser.py
openhands/agenthub/codeact_agent/codeact_agent.py
openhands/agenthub/codeact_agent/function_calling.py
openhands/agenthub/codeact_agent/micro/flarglebargle.md
openhands/agenthub/codeact_agent/micro/github.md
openhands/agenthub/codeact_agent/prompts/default/system_prompt.j2
openhands/agenthub/codeact_agent/prompts/default/user_prompt.j2
openhands/agenthub/codeact_agent/prompts/tools/system_prompt.j2
openhands/agenthub/codeact_agent/prompts/tools/user_prompt.j2
openhands/agenthub/codeact_swe_agent/README.md
openhands/agenthub/codeact_swe_agent/__init__.py
openhands/agenthub/codeact_swe_agent/action_parser.py
openhands/agenthub/codeact_swe_agent/codeact_swe_agent.py
openhands/agenthub/codeact_swe_agent/prompt.py
openhands/agenthub/codeact_swe_agent/response_parser.py
openhands/agenthub/delegator_agent/__init__.py
openhands/agenthub/delegator_agent/agent.py
openhands/agenthub/dummy_agent/__init__.py
openhands/agenthub/dummy_agent/agent.py
openhands/agenthub/micro/README.md
openhands/agenthub/micro/_instructions/actions/browse.md
openhands/agenthub/micro/_instructions/actions/delegate.md
openhands/agenthub/micro/_instructions/actions/finish.md
aact_openhands-0.0.5.dist-info/METADATA
aact_openhands-0.0.5.dist-info/WHEEL
aact_openhands-0.0.5.dist-info/RECORD
