Metadata-Version: 2.1
Name: aact_openhands
Version: 0.0.5
Summary: Openhands integrated with aact
License: MIT
Author: Arpandeep Khatua
Author-email: arpandeepk@gmail.com
Requires-Python: >=3.12,<3.13
Classifier: License :: OSI Approved :: MIT License
Classifier: Programming Language :: Python :: 3
Classifier: Programming Language :: Python :: 3.12
Requires-Dist: aact
Requires-Dist: flask (>=3.0.0,<4.0.0)
Requires-Dist: flask-cors (>=4.0.0,<5.0.0)
Requires-Dist: importlib-resources (>=6.1.1,<7.0.0)
Requires-Dist: pydantic (>=2.6.1,<3.0.0)
Requires-Dist: python-dotenv (>=1.0.0,<2.0.0)
Requires-Dist: rich (>=13.6.0,<14.0.0)
Requires-Dist: websockets (>=12.0.0,<13.0.0)
